pyaemcloudmanagerapi/__init__.py
pyaemcloudmanagerapi/api_client.py
pyaemcloudmanagerapi/configuration.py
pyaemcloudmanagerapi/exceptions.py
pyaemcloudmanagerapi/rest.py
pyaemcloudmanagerapi/api/__init__.py
pyaemcloudmanagerapi/api/branches_api.py
pyaemcloudmanagerapi/api/environments_api.py
pyaemcloudmanagerapi/api/pipeline_execution_api.py
pyaemcloudmanagerapi/api/pipelines_api.py
pyaemcloudmanagerapi/api/programs_api.py
pyaemcloudmanagerapi/api/repositories_api.py
pyaemcloudmanagerapi/api/variables_api.py
pyaemcloudmanagerapi/models/__init__.py
pyaemcloudmanagerapi/models/bad_request_error.py
pyaemcloudmanagerapi/models/branch_list.py
pyaemcloudmanagerapi/models/branch_list_embedded.py
pyaemcloudmanagerapi/models/embedded_program.py
pyaemcloudmanagerapi/models/environment.py
pyaemcloudmanagerapi/models/environment_links.py
pyaemcloudmanagerapi/models/environment_list.py
pyaemcloudmanagerapi/models/environment_list_embedded.py
pyaemcloudmanagerapi/models/environment_log.py
pyaemcloudmanagerapi/models/environment_log_links.py
pyaemcloudmanagerapi/models/environment_logs.py
pyaemcloudmanagerapi/models/environment_logs_embedded.py
pyaemcloudmanagerapi/models/environment_logs_links.py
pyaemcloudmanagerapi/models/hal_link.py
pyaemcloudmanagerapi/models/invalid_parameter.py
pyaemcloudmanagerapi/models/metric.py
pyaemcloudmanagerapi/models/missing_parameter.py
pyaemcloudmanagerapi/models/pipeline.py
pyaemcloudmanagerapi/models/pipeline_execution.py
pyaemcloudmanagerapi/models/pipeline_execution_embedded.py
pyaemcloudmanagerapi/models/pipeline_execution_links.py
pyaemcloudmanagerapi/models/pipeline_execution_list_representation.py
pyaemcloudmanagerapi/models/pipeline_execution_list_representation_embedded.py
pyaemcloudmanagerapi/models/pipeline_execution_list_representation_links.py
pyaemcloudmanagerapi/models/pipeline_execution_step_state.py
pyaemcloudmanagerapi/models/pipeline_execution_step_state_links.py
pyaemcloudmanagerapi/models/pipeline_links.py
pyaemcloudmanagerapi-1.0.0.dist-info/METADATA
pyaemcloudmanagerapi-1.0.0.dist-info/WHEEL
pyaemcloudmanagerapi-1.0.0.dist-info/top_level.txt
pyaemcloudmanagerapi-1.0.0.dist-info/RECORD
