Metadata-Version: 2.1
Name: pyaemcloudmanagerapi
Version: 1.0.0
Summary: Cloud Manager API
Home-page: https://github.com/shinesolutions/cloudmanager-api-clients/tree/master/clients/python/generated
Author: Shine Solutions
Author-email: opensource@shinesolutions.com
License: The Apache License, Version 2.0
Keywords: OpenAPI,OpenAPI-Generator,Cloud Manager API
Platform: UNKNOWN
Requires-Dist: urllib3 (>=1.15)
Requires-Dist: six (>=1.10)
Requires-Dist: certifi
Requires-Dist: python-dateutil
